esrijson/__init__.py
esrijson/base.py
esrijson/codec.py
esrijson/factory.py
esrijson/feature.py
esrijson/geometry.py
esrijson/mapping.py
esrijson/utils.py
esrijson-0.4.4.dist-info/LICENSE
esrijson-0.4.4.dist-info/METADATA
esrijson-0.4.4.dist-info/WHEEL
esrijson-0.4.4.dist-info/top_level.txt
esrijson-0.4.4.dist-info/RECORD
